tensorflow_wavelets/__init__.py
tensorflow_wavelets/Layers/DMWT.py
tensorflow_wavelets/Layers/DTCWT.py
tensorflow_wavelets/Layers/DWT.py
tensorflow_wavelets/Layers/Threshold.py
tensorflow_wavelets/Layers/__init__.py
tensorflow_wavelets/utils/__init__.py
tensorflow_wavelets/utils/canny_edge_detector.py
tensorflow_wavelets/utils/cast.py
tensorflow_wavelets/utils/data.py
tensorflow_wavelets/utils/filters.py
tensorflow_wavelets/utils/helpers.py
tensorflow_wavelets/utils/models.py
tensorflow_wavelets/utils/mse.py
tensorflow_wavelets/utils/plot.py
tensorflow_wavelets/utils/psnt_hvs.py
tensorflow_wavelets/utils/salt_pepper.py
tensorflow_wavelets/utils/ssim.py
tensorflow_wavelets/utils/write_raw.py
tests/__init__.py
tests/test_dwt1d.py
tensorflow_wavelets-1.1.2.dist-info/LICENSE
tensorflow_wavelets-1.1.2.dist-info/METADATA
tensorflow_wavelets-1.1.2.dist-info/WHEEL
tensorflow_wavelets-1.1.2.dist-info/top_level.txt
tensorflow_wavelets-1.1.2.dist-info/RECORD
