Metadata-Version: 2.2
Name: tensorflow-wavelets
Version: 1.1.2
Summary: Tensorflow wavelet Layers
Home-page: https://github.com/Timorleiderman/tensorflow-wavelets
Author: Timor Leiderman
Author-email: Timorleiderman@gmail.com
Project-URL: Bug Tracker, https://github.com/Timorleiderman/tensorflow-wavelets/issues
Keywords: Wavelets,Tensorflow
Classifier: Programming Language :: Python :: 3
Classifier: License :: OSI Approved :: MIT License
Classifier: Operating System :: OS Independent
Requires-Python: >=3.6
License-File: LICENSE
Requires-Dist: tensorflow
Requires-Dist: tensorflow-probability
Requires-Dist: PyWavelets
Dynamic: author
Dynamic: author-email
Dynamic: classifier
Dynamic: description
Dynamic: description-content-type
Dynamic: home-page
Dynamic: keywords
Dynamic: project-url
Dynamic: requires-dist
Dynamic: requires-python
Dynamic: summary
